ovos_chromadb_embeddings/__init__.py
ovos_chromadb_embeddings/version.py
ovos_chromadb_embeddings_plugin-0.0.0.dist-info/METADATA
ovos_chromadb_embeddings_plugin-0.0.0.dist-info/WHEEL
ovos_chromadb_embeddings_plugin-0.0.0.dist-info/entry_points.txt
ovos_chromadb_embeddings_plugin-0.0.0.dist-info/top_level.txt
ovos_chromadb_embeddings_plugin-0.0.0.dist-info/zip-safe
ovos_chromadb_embeddings_plugin-0.0.0.dist-info/RECORD
