Metadata-Version: 2.1
Name: ovos-chromadb-embeddings-plugin
Version: 0.0.0
Summary: A chromadb embeddings plugin for OVOS
Home-page: https://github.com/TigreGotico/ovos-chromadb-embeddings-plugin
Author: jarbasai
Author-email: jarbasai@mailfence.com
License: MIT
Keywords: OVOS openvoiceos plugin chromadb recognition
Platform: UNKNOWN
Requires-Dist: ovos-plugin-manager
Requires-Dist: numpy
Requires-Dist: chromadb
